Qt.py
Qt_convert_enum.py
Qt-stubs/Qt.pyi
Qt-stubs/QtBluetooth.pyi
Qt-stubs/QtCompat.pyi
Qt-stubs/QtCore.pyi
Qt-stubs/QtDBus.pyi
Qt-stubs/QtDesigner.pyi
Qt-stubs/QtGui.pyi
Qt-stubs/QtHelp.pyi
Qt-stubs/QtLocation.pyi
Qt-stubs/QtMultimedia.pyi
Qt-stubs/QtMultimediaWidgets.pyi
Qt-stubs/QtNetwork.pyi
Qt-stubs/QtNfc.pyi
Qt-stubs/QtOpenGL.pyi
Qt-stubs/QtPositioning.pyi
Qt-stubs/QtPrintSupport.pyi
Qt-stubs/QtQml.pyi
Qt-stubs/QtQuick.pyi
Qt-stubs/QtQuickWidgets.pyi
Qt-stubs/QtSensors.pyi
Qt-stubs/QtSerialPort.pyi
Qt-stubs/QtSql.pyi
Qt-stubs/QtSvg.pyi
Qt-stubs/QtTest.pyi
Qt-stubs/QtWebChannel.pyi
Qt-stubs/QtWebEngineCore.pyi
Qt-stubs/QtWebEngineWidgets.pyi
Qt-stubs/QtWebKit.pyi
Qt-stubs/QtWebKitWidgets.pyi
Qt-stubs/QtWebSockets.pyi
Qt-stubs/QtWidgets.pyi
Qt-stubs/QtX11Extras.pyi
Qt-stubs/QtXml.pyi
Qt-stubs/QtXmlPatterns.pyi
Qt-stubs/__init__.pyi
qt_py-2.0.2.dist-info/licenses/LICENSE
qt_py-2.0.2.dist-info/METADATA
qt_py-2.0.2.dist-info/WHEEL
qt_py-2.0.2.dist-info/top_level.txt
qt_py-2.0.2.dist-info/RECORD
