Metadata-Version: 2.4
Name: Qt.py
Version: 2.0.2
Summary: Python compatibility wrapper around Qt5 and Qt6 bindings - PySide2, PySide6, PyQt5 and PyQt6.
Author-email: Marcus Ottosson <konstruktion@gmail.com>
License: MIT
Project-URL: Homepage, https://github.com/mottosso/Qt
Project-URL: Source, https://github.com/mottosso/Qt
Project-URL: Repository, https://github.com/mottosso/Qt
Project-URL: Issues, https://github.com/mottosso/Qt.py/issues
Classifier: Development Status :: 4 - Beta
Classifier: Intended Audience :: Developers
Classifier: Programming Language :: Python
Classifier: Programming Language :: Python :: 3
Classifier: Programming Language :: Python :: 3.7
Classifier: Programming Language :: Python :: 3.9
Classifier: Programming Language :: Python :: 3.10
Classifier: Programming Language :: Python :: 3.11
Classifier: Topic :: Software Development :: Libraries :: Python Modules
Classifier: Topic :: Utilities
Requires-Python: >=3.7
License-File: LICENSE
Requires-Dist: types-PySide2
Provides-Extra: dev
Requires-Dist: ruff; extra == "dev"
Requires-Dist: tox<5,>=4; extra == "dev"
Dynamic: license-file
